pytgauth/__init__.py
pytgauth-0.0.2.dist-info/LICENSE
pytgauth-0.0.2.dist-info/METADATA
pytgauth-0.0.2.dist-info/WHEEL
pytgauth-0.0.2.dist-info/top_level.txt
pytgauth-0.0.2.dist-info/RECORD
