Metadata-Version: 2.1
Name: pytgauth
Version: 0.0.2
Summary: A Wrapper to verify Telegram auth data while Web login.
Home-page: https://github.com/jainamoswal/pytgauth
Author: Jainam Oswal
Author-email: Jainamoswal@gmail.com
License: GPLv3
Project-URL: Documentation, https://github.com/jainamoswal/pytgauth
Project-URL: Channel, https://t.me/j_projects
Project-URL: Source Code, https://github.com/jainamoswal/pytgauth
Project-URL: Support, https://t.me/j_projects_chat
Platform: UNKNOWN
Classifier: Programming Language :: Python :: 3
Classifier: License :: OSI Approved :: GNU General Public License v3 (GPLv3)
Classifier: Operating System :: OS Independent
Classifier: Framework :: Flask
Requires-Python: >=3.6
